pmodhygro/__init__.py
pmodhygro/pmodhygro.py
pmodhygro-1.0.3.dist-info/METADATA
pmodhygro-1.0.3.dist-info/WHEEL
pmodhygro-1.0.3.dist-info/top_level.txt
pmodhygro-1.0.3.dist-info/RECORD
